CHANGES.rst
COPYING
COPYING.LESSER
MANIFEST.in
README.rst
bootstrap-buildout.py
buildout.cfg
ez_setup.py
setup.cfg
setup.py
tox.ini
./mete0r_olefilefs/__init__.py
./mete0r_olefilefs/cli.py
./mete0r_olefilefs/fs.py
./mete0r_olefilefs/opener.py
./mete0r_olefilefs/tests/__init__.py
./mete0r_olefilefs/tests/test_fs.py
./mete0r_olefilefs/tests/test_opener.py
./mete0r_olefilefs/tests/files/example.stg
./mete0r_olefilefs/tests/files/test.xls
mete0r.olefilefs.egg-info/PKG-INFO
mete0r.olefilefs.egg-info/SOURCES.txt
mete0r.olefilefs.egg-info/dependency_links.txt
mete0r.olefilefs.egg-info/entry_points.txt
mete0r.olefilefs.egg-info/not-zip-safe
mete0r.olefilefs.egg-info/requires.txt
mete0r.olefilefs.egg-info/top_level.txt
mete0r_olefilefs/tests/files/example.stg
mete0r_olefilefs/tests/files/test.xls