Metadata-Version: 1.1
Name: mete0r.olefilefs
Version: 0.1.0
Summary: PyFilesystem interface to olefile
Home-page: https://github.com/mete0r/mete0r.olefilefs
Author: mete0r
Author-email: mete0r@sarangbang.or.kr
License: GNU Lesser General Public License v3 or later (LGPLv3+)
Keywords: PyFilesystem,fs,ole,olefile
Platform: UNKNOWN
Classifier: Development Status :: 3 - Alpha
Classifier: Intended Audience :: Developers
Classifier: License :: OSI Approved :: GNU Lesser General Public License v3 or later (LGPLv3+)
Classifier: Operating System :: OS Independent
Classifier: Programming Language :: Python
Classifier: Programming Language :: Python :: 2.7
Classifier: Programming Language :: Python :: 3.4
Classifier: Programming Language :: Python :: Implementation :: CPython
Classifier: Programming Language :: Python :: Implementation :: PyPy
